{"ICI":[{"iso3":"ALB","rank":1467,"share":0.0,"contribution":0.0},{"iso3":"ARE","rank":3128,"share":0.0,"contribution":0.0},{"iso3":"ARG","rank":2582,"share":0.0,"contribution":0.0},{"iso3":"ARM","rank":1472,"share":0.0,"contribution":0.0},{"iso3":"AUS","rank":2460,"share":0.0,"contribution":0.0},{"iso3":"AUT","rank":3171,"share":0.0,"contribution":0.0},{"iso3":"AZE","rank":1524,"share":0.0,"contribution":0.0},{"iso3":"BEL","rank":3340,"share":0.0,"contribution":0.0},{"iso3":"BFA","rank":486,"share":0.0,"contribution":0.0},{"iso3":"BGD","rank":1820,"share":0.0,"contribution":0.0},{"iso3":"BGR","rank":2634,"share":0.0,"contribution":0.0},{"iso3":"BHR","rank":2230,"share":0.0,"contribution":0.0},{"iso3":"BLR","rank":1725,"share":0.0,"contribution":0.0},{"iso3":"BRA","rank":2042,"share":0.0,"contribution":0.0},{"iso3":"BRB","rank":1139,"share":0.0,"contribution":0.0},{"iso3":"BRN","rank":1224,"share":0.0,"contribution":0.0},{"iso3":"CAN","rank":874,"share":0.0,"contribution":0.0},{"iso3":"CHE","rank":3369,"share":0.0,"contribution":0.0},{"iso3":"CHL","rank":2799,"share":0.0,"contribution":0.0},{"iso3":"COL","rank":2899,"share":0.0,"contribution":0.0},{"iso3":"CYP","rank":2307,"share":0.0,"contribution":0.0},{"iso3":"CZE","rank":3026,"share":0.0,"contribution":0.0},{"iso3":"DEU","rank":3346,"share":0.0,"contribution":0.0},{"iso3":"DNK","rank":3078,"share":0.0,"contribution":0.0},{"iso3":"DOM","rank":1716,"share":0.0,"contribution":0.0},{"iso3":"DZA","rank":1202,"share":0.0,"contribution":0.0},{"iso3":"ECU","rank":2235,"share":0.0,"contribution":0.0},{"iso3":"EGY","rank":2638,"share":0.0,"contribution":0.0},{"iso3":"ESP","rank":3291,"share":0.0,"contribution":0.0},{"iso3":"EST","rank":2647,"share":0.0,"contribution":0.0},{"iso3":"ETH","rank":1074,"share":0.0,"contribution":0.0},{"iso3":"FIN","rank":2959,"share":0.0,"contribution":0.0},{"iso3":"FRA","rank":3220,"share":0.0,"contribution":0.0},{"iso3":"GAB","rank":560,"share":0.0,"contribution":0.0},{"iso3":"GBR","rank":3178,"share":0.0,"contribution":0.0},{"iso3":"GEO","rank":1930,"share":0.0,"contribution":0.0},{"iso3":"GHA","rank":1888,"share":0.0,"contribution":0.0},{"iso3":"GRC","rank":2838,"share":0.0,"contribution":0.0},{"iso3":"GTM","rank":2701,"share":0.0,"contribution":0.0},{"iso3":"HKG","rank":3225,"share":0.0,"contribution":0.0},{"iso3":"HND","rank":2025,"share":0.0,"contribution":0.0},{"iso3":"HRV","rank":2748,"share":0.0,"contribution":0.0},{"iso3":"HUN","rank":2961,"share":0.0,"contribution":0.0},{"iso3":"IDN","rank":3368,"share":0.0,"contribution":0.0},{"iso3":"IRL","rank":3267,"share":0.0,"contribution":0.0},{"iso3":"IRN","rank":2079,"share":0.0,"contribution":0.0},{"iso3":"ISL","rank":1906,"share":0.0,"contribution":0.0},{"iso3":"ITA","rank":3180,"share":0.0,"contribution":0.0},{"iso3":"JAM","rank":797,"share":0.0,"contribution":0.0},{"iso3":"JOR","rank":2110,"share":0.0,"contribution":0.0},{"iso3":"JPN","rank":2988,"share":0.0,"contribution":0.0},{"iso3":"KAZ","rank":2556,"share":0.0,"contribution":0.0},{"iso3":"KEN","rank":2369,"share":0.0,"contribution":0.0},{"iso3":"KGZ","rank":1431,"share":0.0,"contribution":0.0},{"iso3":"KHM","rank":1309,"share":0.0,"contribution":0.0},{"iso3":"KOR","rank":2563,"share":0.0,"contribution":0.0},{"iso3":"KWT","rank":1565,"share":0.0,"contribution":0.0},{"iso3":"LBN","rank":1905,"share":0.0,"contribution":0.0},{"iso3":"LTU","rank":2626,"share":0.0,"contribution":0.0},{"iso3":"LUX","rank":1859,"share":0.0,"contribution":0.0},{"iso3":"LVA","rank":2680,"share":0.0,"contribution":0.0},{"iso3":"MAR","rank":2540,"share":0.0,"contribution":0.0},{"iso3":"MEX","rank":1790,"share":0.0,"contribution":0.0},{"iso3":"MLT","rank":2143,"share":0.0,"contribution":0.0},{"iso3":"MOZ","rank":1133,"share":0.0,"contribution":0.0},{"iso3":"MYS","rank":3402,"share":0.0,"contribution":0.0},{"iso3":"NGA","rank":1777,"share":0.0,"contribution":0.0},{"iso3":"NLD","rank":3439,"share":0.0,"contribution":0.0},{"iso3":"NOR","rank":2989,"share":0.0,"contribution":0.0},{"iso3":"OMN","rank":1576,"share":0.0,"contribution":0.0},{"iso3":"PAK","rank":2550,"share":0.0,"contribution":0.0},{"iso3":"PAN","rank":2285,"share":0.0,"contribution":0.0},{"iso3":"PER","rank":2755,"share":0.0,"contribution":0.0},{"iso3":"PHL","rank":2810,"share":0.0,"contribution":0.0},{"iso3":"POL","rank":3230,"share":0.0,"contribution":0.0},{"iso3":"PRT","rank":2923,"share":0.0,"contribution":0.0},{"iso3":"PRY","rank":1320,"share":0.0,"contribution":0.0},{"iso3":"QAT","rank":1773,"share":0.0,"contribution":0.0},{"iso3":"ROU","rank":2897,"share":0.0,"contribution":0.0},{"iso3":"RUS","rank":2599,"share":0.0,"contribution":0.0},{"iso3":"SAU","rank":2976,"share":0.0,"contribution":0.0},{"iso3":"SGP","rank":2893,"share":0.0,"contribution":0.0},{"iso3":"SRB","rank":2728,"share":0.0,"contribution":0.0},{"iso3":"SUR","rank":585,"share":0.0,"contribution":0.0},{"iso3":"SVK","rank":2786,"share":0.0,"contribution":0.0},{"iso3":"SVN","rank":2610,"share":0.0,"contribution":0.0},{"iso3":"SWE","rank":3196,"share":0.0,"contribution":0.0},{"iso3":"THA","rank":3438,"share":0.0,"contribution":0.0},{"iso3":"TTO","rank":1155,"share":0.0,"contribution":0.0},{"iso3":"TUN","rank":1731,"share":0.0,"contribution":0.0},{"iso3":"TUR","rank":3312,"share":0.0,"contribution":0.0},{"iso3":"TZA","rank":1753,"share":0.0,"contribution":0.0},{"iso3":"UKR","rank":2768,"share":0.0,"contribution":0.0},{"iso3":"URY","rank":1844,"share":0.0,"contribution":0.0},{"iso3":"USA","rank":2636,"share":0.0,"contribution":0.0},{"iso3":"VNM","rank":3134,"share":0.0,"contribution":0.0},{"iso3":"ZAF","rank":3218,"share":0.0,"contribution":0.0},{"iso3":"ZMB","rank":1702,"share":0.0,"contribution":0.0},{"iso3":"ZWE","rank":1139,"share":0.0,"contribution":0.0}],"ECI":[{"iso3":"ALB","rank":2021,"share":0.0,"contribution":0.0},{"iso3":"ARM","rank":2392,"share":0.0,"contribution":0.0},{"iso3":"AUS","rank":3195,"share":0.0,"contribution":0.0},{"iso3":"AUT","rank":3728,"share":0.0,"contribution":0.0},{"iso3":"BEL","rank":3795,"share":0.0,"contribution":0.0},{"iso3":"BIH","rank":2723,"share":0.0,"contribution":0.0},{"iso3":"BRA","rank":2235,"share":0.0,"contribution":0.0},{"iso3":"BRN","rank":1899,"share":0.0,"contribution":0.0},{"iso3":"CAN","rank":3655,"share":0.0,"contribution":0.0},{"iso3":"CHE","rank":3711,"share":0.0,"contribution":0.0},{"iso3":"COL","rank":2743,"share":0.0,"contribution":0.0},{"iso3":"CYP","rank":2950,"share":0.0,"contribution":0.0},{"iso3":"DEU","rank":3836,"share":0.0,"contribution":0.0},{"iso3":"DNK","rank":3692,"share":0.0,"contribution":0.0},{"iso3":"ESP","rank":3813,"share":0.0,"contribution":0.0},{"iso3":"ETH","rank":1491,"share":0.0,"contribution":0.0},{"iso3":"FRA","rank":3829,"share":0.0,"contribution":0.0},{"iso3":"GEO","rank":2468,"share":0.0,"contribution":0.0},{"iso3":"GRC","rank":3594,"share":0.0,"contribution":0.0},{"iso3":"HKG","rank":2978,"share":0.0,"contribution":0.0},{"iso3":"HRV","rank":3458,"share":0.0,"contribution":0.0},{"iso3":"HUN","rank":3031,"share":0.0,"contribution":0.0},{"iso3":"IDN","rank":3585,"share":0.0,"contribution":0.0},{"iso3":"IND","rank":3745,"share":0.0,"contribution":0.0},{"iso3":"ITA","rank":3191,"share":0.0,"contribution":0.0},{"iso3":"JPN","rank":3062,"share":0.0,"contribution":0.0},{"iso3":"KGZ","rank":1889,"share":0.0,"contribution":0.0},{"iso3":"KHM","rank":2209,"share":0.0,"contribution":0.0},{"iso3":"LBN","rank":2260,"share":0.0,"contribution":0.0},{"iso3":"LTU","rank":3526,"share":0.0,"contribution":0.0},{"iso3":"LUX","rank":3500,"share":0.0,"contribution":0.0},{"iso3":"LVA","rank":3447,"share":0.0,"contribution":0.0},{"iso3":"MLT","rank":3074,"share":0.0,"contribution":0.0},{"iso3":"MYS","rank":2838,"share":0.0,"contribution":0.0},{"iso3":"NGA","rank":1913,"share":0.0,"contribution":0.0},{"iso3":"NLD","rank":3374,"share":0.0,"contribution":0.0},{"iso3":"OMN","rank":1956,"share":0.0,"contribution":0.0},{"iso3":"PAK","rank":2698,"share":0.0,"contribution":0.0},{"iso3":"POL","rank":3751,"share":0.0,"contribution":0.0},{"iso3":"QAT","rank":2146,"share":0.0,"contribution":0.0},{"iso3":"ROU","rank":3621,"share":0.0,"contribution":0.0},{"iso3":"RUS","rank":2530,"share":0.0,"contribution":0.0},{"iso3":"SAU","rank":3094,"share":0.0,"contribution":0.0},{"iso3":"SGP","rank":3693,"share":0.0,"contribution":0.0},{"iso3":"SRB","rank":3202,"share":0.0,"contribution":0.0},{"iso3":"SVN","rank":3597,"share":0.0,"contribution":0.0},{"iso3":"THA","rank":3269,"share":0.0,"contribution":0.0},{"iso3":"TUR","rank":2963,"share":0.0,"contribution":0.0},{"iso3":"TZA","rank":2091,"share":0.0,"contribution":0.0},{"iso3":"UKR","rank":3200,"share":0.0,"contribution":0.0},{"iso3":"USA","rank":2678,"share":0.0,"contribution":0.0},{"iso3":"VNM","rank":3484,"share":0.0,"contribution":0.0},{"iso3":"ZAF","rank":3454,"share":0.0,"contribution":0.0}],"SGI":[{"iso3":"ALB","rank":2333,"share":0.0,"contribution":0.0},{"iso3":"ARE","rank":944,"share":0.0,"contribution":0.0},{"iso3":"ARG","rank":104,"share":0.05,"contribution":0.0},{"iso3":"ARM","rank":2571,"share":0.0,"contribution":0.0},{"iso3":"AUS","rank":3342,"share":0.0,"contribution":0.0},{"iso3":"AUT","rank":2287,"share":0.0,"contribution":0.0},{"iso3":"AZE","rank":2184,"share":0.0,"contribution":0.0},{"iso3":"BEL","rank":2597,"share":0.0,"contribution":0.0},{"iso3":"BFA","rank":60,"share":0.09,"contribution":0.0},{"iso3":"BGD","rank":290,"share":0.0,"contribution":0.0},{"iso3":"BGR","rank":2581,"share":0.0,"contribution":0.0},{"iso3":"BHR","rank":1992,"share":0.0,"contribution":0.0},{"iso3":"BIH","rank":3079,"share":0.0,"contribution":0.0},{"iso3":"BLR","rank":2382,"share":0.0,"contribution":0.0},{"iso3":"BRA","rank":86,"share":0.06,"contribution":0.0},{"iso3":"BRN","rank":1991,"share":0.0,"contribution":0.0},{"iso3":"BWA","rank":2223,"share":0.0,"contribution":0.0},{"iso3":"CAF","rank":508,"share":0.0,"contribution":0.0},{"iso3":"CAN","rank":3230,"share":0.0,"contribution":0.0},{"iso3":"CHE","rank":4195,"share":0.0,"contribution":0.0},{"iso3":"CHL","rank":2758,"share":0.0,"contribution":0.0},{"iso3":"COD","rank":1289,"share":0.0,"contribution":0.0},{"iso3":"COL","rank":524,"share":0.01,"contribution":0.0},{"iso3":"CYP","rank":764,"share":0.0,"contribution":0.0},{"iso3":"CZE","rank":1972,"share":0.0,"contribution":0.0},{"iso3":"DEU","rank":3173,"share":0.0,"contribution":0.0},{"iso3":"DNK","rank":3224,"share":0.0,"contribution":0.0},{"iso3":"DOM","rank":2402,"share":0.0,"contribution":0.0},{"iso3":"DZA","rank":1607,"share":0.0,"contribution":0.0},{"iso3":"ECU","rank":2526,"share":0.0,"contribution":0.0},{"iso3":"EGY","rank":347,"share":0.02,"contribution":0.0},{"iso3":"ESP","rank":1342,"share":0.0,"contribution":0.0},{"iso3":"EST","rank":1152,"share":0.0,"contribution":0.0},{"iso3":"ETH","rank":67,"share":0.04,"contribution":0.0},{"iso3":"FIN","rank":2648,"share":0.0,"contribution":0.0},{"iso3":"FRA","rank":1717,"share":0.0,"contribution":0.0},{"iso3":"GAB","rank":927,"share":0.0,"contribution":0.0},{"iso3":"GBR","rank":3803,"share":0.0,"contribution":0.0},{"iso3":"GEO","rank":2732,"share":0.0,"contribution":0.0},{"iso3":"GHA","rank":2538,"share":0.0,"contribution":0.0},{"iso3":"GNB","rank":345,"share":0.0,"contribution":0.0},{"iso3":"GRC","rank":2382,"share":0.0,"contribution":0.0},{"iso3":"GTM","rank":3085,"share":0.0,"contribution":0.0},{"iso3":"HKG","rank":2857,"share":0.0,"contribution":0.0},{"iso3":"HND","rank":1859,"share":0.0,"contribution":0.0},{"iso3":"HRV","rank":1956,"share":0.0,"contribution":0.0},{"iso3":"HUN","rank":375,"share":0.02,"contribution":0.0},{"iso3":"IDN","rank":3213,"share":0.0,"contribution":0.0},{"iso3":"IND","rank":3716,"share":0.0,"contribution":0.0},{"iso3":"IRL","rank":3308,"share":0.0,"contribution":0.0},{"iso3":"IRN","rank":2819,"share":0.0,"contribution":0.0},{"iso3":"ISL","rank":2529,"share":0.0,"contribution":0.0},{"iso3":"ITA","rank":2047,"share":0.0,"contribution":0.0},{"iso3":"JOR","rank":2558,"share":0.0,"contribution":0.0},{"iso3":"JPN","rank":2214,"share":0.0,"contribution":0.0},{"iso3":"KAZ","rank":3081,"share":0.0,"contribution":0.0},{"iso3":"KEN","rank":2123,"share":0.0,"contribution":0.0},{"iso3":"KGZ","rank":2032,"share":0.0,"contribution":0.0},{"iso3":"KHM","rank":2275,"share":0.0,"contribution":0.0},{"iso3":"KOR","rank":1177,"share":0.0,"contribution":0.0},{"iso3":"KWT","rank":1941,"share":0.0,"contribution":0.0},{"iso3":"LBN","rank":1700,"share":0.0,"contribution":0.0},{"iso3":"LBR","rank":826,"share":0.0,"contribution":0.0},{"iso3":"LBY","rank":810,"share":0.0,"contribution":0.0},{"iso3":"LSO","rank":963,"share":0.0,"contribution":0.0},{"iso3":"LTU","rank":3130,"share":0.0,"contribution":0.0},{"iso3":"LUX","rank":3063,"share":0.0,"contribution":0.0},{"iso3":"LVA","rank":3075,"share":0.0,"contribution":0.0},{"iso3":"MAR","rank":2428,"share":0.0,"contribution":0.0},{"iso3":"MEX","rank":2937,"share":0.0,"contribution":0.0},{"iso3":"MHL","rank":767,"share":0.0,"contribution":0.0},{"iso3":"MLT","rank":2194,"share":0.0,"contribution":0.0},{"iso3":"MOZ","rank":1734,"share":0.0,"contribution":0.0},{"iso3":"MYS","rank":1584,"share":0.0,"contribution":0.0},{"iso3":"NAM","rank":2560,"share":0.0,"contribution":0.0},{"iso3":"NGA","rank":1842,"share":0.0,"contribution":0.0},{"iso3":"NLD","rank":2520,"share":0.0,"contribution":0.0},{"iso3":"NOR","rank":3260,"share":0.0,"contribution":0.0},{"iso3":"OMN","rank":2118,"share":0.0,"contribution":0.0},{"iso3":"PAK","rank":3016,"share":0.0,"contribution":0.0},{"iso3":"PAN","rank":2796,"share":0.0,"contribution":0.0},{"iso3":"PER","rank":2948,"share":0.0,"contribution":0.0},{"iso3":"PHL","rank":3277,"share":0.0,"contribution":0.0},{"iso3":"POL","rank":2370,"share":0.0,"contribution":0.0},{"iso3":"PRT","rank":1791,"share":0.0,"contribution":0.0},{"iso3":"PRY","rank":328,"share":0.0,"contribution":0.0},{"iso3":"QAT","rank":2327,"share":0.0,"contribution":0.0},{"iso3":"ROU","rank":1897,"share":0.0,"contribution":0.0},{"iso3":"RUS","rank":2555,"share":0.0,"contribution":0.0},{"iso3":"SAU","rank":1026,"share":0.0,"contribution":0.0},{"iso3":"SGP","rank":2606,"share":0.0,"contribution":0.0},{"iso3":"SRB","rank":1165,"share":0.0,"contribution":0.0},{"iso3":"SUR","rank":1104,"share":0.0,"contribution":0.0},{"iso3":"SVK","rank":1165,"share":0.0,"contribution":0.0},{"iso3":"SVN","rank":2111,"share":0.0,"contribution":0.0},{"iso3":"SWE","rank":2579,"share":0.0,"contribution":0.0},{"iso3":"THA","rank":3489,"share":0.0,"contribution":0.0},{"iso3":"TUN","rank":2659,"share":0.0,"contribution":0.0},{"iso3":"TUR","rank":477,"share":0.03,"contribution":0.0},{"iso3":"TZA","rank":145,"share":0.04,"contribution":0.0},{"iso3":"UKR","rank":1350,"share":0.0,"contribution":0.0},{"iso3":"URY","rank":585,"share":0.0,"contribution":0.0},{"iso3":"USA","rank":851,"share":0.01,"contribution":0.0},{"iso3":"VNM","rank":3777,"share":0.0,"contribution":0.0},{"iso3":"ZAF","rank":769,"share":0.0,"contribution":0.0},{"iso3":"ZMB","rank":1924,"share":0.0,"contribution":0.0},{"iso3":"ZWE","rank":1555,"share":0.0,"contribution":0.0}],"CGI":[{"iso3":"CAN","rank":2594,"share":0.0,"contribution":0.0},{"iso3":"ITA","rank":3128,"share":0.0,"contribution":0.0},{"iso3":"KAZ","rank":2400,"share":0.0,"contribution":0.0},{"iso3":"KOR","rank":2847,"share":0.0,"contribution":0.0},{"iso3":"SGP","rank":2352,"share":0.0,"contribution":0.0},{"iso3":"THA","rank":3364,"share":0.0,"contribution":0.0},{"iso3":"USA","rank":2758,"share":0.0,"contribution":0.0}]}